crowdlaw/__init__.py
crowdlaw/main.py
crowdlaw/api/__init__.py
crowdlaw/api/api.py
crowdlaw/api/gitlab_api.py
crowdlaw/controller/__init__.py
crowdlaw/controller/common.py
crowdlaw/controller/language.py
crowdlaw/controller/main_window.py
crowdlaw/controller/on_boarding.py
crowdlaw/git_adapter/__init__.py
crowdlaw/git_adapter/git_adapter.py
crowdlaw/locale/en_US/LC_MESSAGES/crowdlaw.mo
crowdlaw/locale/en_US/LC_MESSAGES/crowdlaw.po
crowdlaw/locale/pl_PL/LC_MESSAGES/crowdlaw.mo
crowdlaw/locale/pl_PL/LC_MESSAGES/crowdlaw.po
crowdlaw/model/__init__.py
crowdlaw/model/common.py
crowdlaw/model/main_window.py
crowdlaw/model/on_boarding.py
crowdlaw/resources/VERSION
crowdlaw/resources/git_providers.yaml
crowdlaw/resources/stages.yaml
crowdlaw/resources/icons/question-circle-regular.png
crowdlaw/resources/images/gitlab_pat.png
crowdlaw/utils/__init__.py
crowdlaw/utils/supported_langs.py
crowdlaw/utils/utils.py
crowdlaw/views/__init__.py
crowdlaw/views/common.py
crowdlaw/views/main_window.py
crowdlaw/views/on_boarding.py
crowdlaw-1.0.0.dist-info/METADATA
crowdlaw-1.0.0.dist-info/WHEEL
crowdlaw-1.0.0.dist-info/entry_points.txt
crowdlaw-1.0.0.dist-info/license.txt
crowdlaw-1.0.0.dist-info/top_level.txt
crowdlaw-1.0.0.dist-info/RECORD
