Metadata-Version: 2.1
Name: crowdlaw
Version: 1.0.0
Summary: Create and edit law collaboratively
Home-page: https://gitlab.com/gladykov/crowdlaw/
Author: Jakub Gładykowski
Author-email: gladykov@gmail.com
License: GPLv3
Platform: any
Classifier: Development Status :: 3 - Alpha
Classifier: License :: OSI Approved :: GNU General Public License v3 (GPLv3)
Classifier: Programming Language :: Python :: 3
Classifier: Programming Language :: Python :: 3.10
License-File: license.txt
Requires-Dist: python-gitlab (==2.*)
Requires-Dist: GitPython (==3.*)
Requires-Dist: PySimpleGUI (==4.*)
Requires-Dist: PyYAML (==5.*)
Requires-Dist: validators (==0.*)
Requires-Dist: requests (==2.*)
Requires-Dist: pyperclip (==1.*)
